<?xml version="1.0" encoding="UTF-8"?>
<!DOCTYPE jasperReport PUBLIC "-//JasperReports//DTD Report Design//EN" "/usr/local/emaku/reports/dtd/jasperreport.dtd">
<jasperReport name="EmakuReport" pageWidth="595" pageHeight="842" columnWidth="555" leftMargin="20" rightMargin="20" topMargin="30" bottomMargin="30" language="java" columnCount="1" printOrder="Vertical" orientation="Portrait" whenNoDataType="NoPages" columnSpacing="0" isTitleNewPage="false" isSummaryNewPage="false" isFloatColumnFooter="false" whenResourceMissingType="Null" isIgnorePagination="false">
	<style name="eMaku-Font1" isDefault="false" fontName="Arial" fontSize="12" isBold="false" pdfFontName="Helvetica-Bold" pdfEncoding="Cp1252" isPdfEmbedded="false" />
	<style name="eMaku-Font2" isDefault="false" fontName="Arial" fontSize="8" isBold="false" pdfFontName="Helvetica-Bold" pdfEncoding="Cp1252" isPdfEmbedded="false" />
	<style name="eMaku-Font3" isDefault="false" fontName="Arial" fontSize="18" isBold="true" pdfFontName="Helvetica-Bold" pdfEncoding="Cp1252" isPdfEmbedded="false" />
	<style name="eMaku-Font4" isDefault="false" fontName="Arial" fontSize="13" isBold="true" pdfFontName="Helvetica-Bold" pdfEncoding="Cp1252" isPdfEmbedded="false" />
	<style name="eMaku-Font5" isDefault="false" fontName="Arial" fontSize="12" isBold="true" pdfFontName="Helvetica-Bold" pdfEncoding="Cp1252" isPdfEmbedded="false" />
	<style name="eMaku-Font6" isDefault="false" fontName="Arial" fontSize="10" isBold="true" pdfFontName="Helvetica-Bold" pdfEncoding="Cp1252" isPdfEmbedded="false" />

	<parameter name="Empresa" class="java.lang.String" isForPrompting="true" />
	<parameter name="Nit" class="java.lang.String" isForPrompting="true" />
	<parameter name="Fecha" class="java.lang.String" isForPrompting="true" />
	<parameter name="Qhatu" class="java.lang.String" isForPrompting="true" />
	<parameter name="Url" class="java.lang.String" isForPrompting="true" />
	<code>CRE0030</code>
	<sqlCode>DGSEL0090</sqlCode>
	<name>Lista de Precios por Grupo</name>

	<field name="nombre" class="java.lang.String" />
	<field name="descr_grupo" class="java.lang.String" />
	<field name="codigo" class="java.lang.String" />
	<field name="descr_producto" class="java.lang.String" />
	<field name="iva" class="java.lang.String" />
	<field name="pventa" class="java.lang.Double" />
            <field name="pcompra" class="java.lang.Double" />
	<field name="neto" class="java.lang.Double" />

	<group name="EncabezadoCatalogo" isReprintHeaderOnEachPage="true" isStartNewColumn="false" isStartNewPage="true" isResetPageNumber="false" minHeightToStartNewPage="0">
		<groupExpression>
			<![CDATA[$F{nombre}]]>
		</groupExpression>
		<groupHeader>
			<band height="30" isSplitAllowed="true">
				<line direction="TopDown">
					<reportElement x="0" y="0" width="540" height="1" positionType="FixRelativeToTop" stretchType="NoStretch" isPrintRepeatedValues="true" isRemoveLineWhenBlank="false" isPrintInFirstWholeBand="false" isPrintWhenDetailOverflows="false" />
					<graphicElement />
				</line>
				<textField isStretchWithOverflow="false" evaluationTime="Now" hyperlinkType="None" hyperlinkTarget="Self" bookmarkLevel="0">
					<reportElement x="0" y="10" width="555" height="20" style="eMaku-Font6" positionType="FixRelativeToTop" stretchType="NoStretch" isPrintRepeatedValues="true" isRemoveLineWhenBlank="false" isPrintInFirstWholeBand="false" isPrintWhenDetailOverflows="false" />
				<textElement textAlignment="Center" />
					<textFieldExpression class="java.lang.String">
						<![CDATA[$F{nombre}]]>
					</textFieldExpression>
				</textField>
			</band>
		</groupHeader>
		<groupFooter>
			<band height="0" isSplitAllowed="true" />
		</groupFooter>
	</group>
	<group name="EncabezadoGrupo" isReprintHeaderOnEachPage="true" isStartNewColumn="false" isStartNewPage="true" isResetPageNumber="false" minHeightToStartNewPage="0">
		<groupExpression>
			<![CDATA[$F{descr_grupo}]]>
		</groupExpression>
		<groupHeader>
			<band height="50" isSplitAllowed="true">
				<line direction="TopDown">
					<reportElement x="0" y="20" width="540" height="1" positionType="FixRelativeToTop" stretchType="NoStretch" isPrintRepeatedValues="true" isRemoveLineWhenBlank="false" isPrintInFirstWholeBand="false" isPrintWhenDetailOverflows="false" />
					<graphicElement />
				</line>
		<staticText>
			<reportElement x="30" y="25" width="555" height="15" style="eMaku-Font6" positionType="FixRelativeToTop" stretchType="NoStretch" isPrintRepeatedValues="true" isRemoveLineWhenBlank="false" isPrintInFirstWholeBand="false" isPrintWhenDetailOverflows="false" />
			<textElement>
				<font />
			</textElement>
			<text><![CDATA[C칩digo]]></text>
		</staticText>
		<staticText>
			<reportElement x="150" y="25" width="555" height="15" style="eMaku-Font6" positionType="FixRelativeToTop" stretchType="NoStretch" isPrintRepeatedValues="true" isRemoveLineWhenBlank="false" isPrintInFirstWholeBand="false" isPrintWhenDetailOverflows="false" />
			<textElement>
				<font />
			</textElement>
			<text><![CDATA[Descripci칩n]]></text>
		</staticText>
		<staticText>
			<reportElement x="320" y="25" width="555" height="15" style="eMaku-Font6" positionType="FixRelativeToTop" stretchType="NoStretch" isPrintRepeatedValues="true" isRemoveLineWhenBlank="false" isPrintInFirstWholeBand="false" isPrintWhenDetailOverflows="false" />
			<textElement>
				<font />
			</textElement>
			<text><![CDATA[P. Compra]]></text>
		</staticText>
		<staticText>
			<reportElement x="380" y="25" width="555" height="15" style="eMaku-Font6" positionType="FixRelativeToTop" stretchType="NoStretch" isPrintRepeatedValues="true" isRemoveLineWhenBlank="false" isPrintInFirstWholeBand="false" isPrintWhenDetailOverflows="false" />
			<textElement>
				<font />
			</textElement>
			<text><![CDATA[V. Unitario]]></text>
		</staticText>
		<staticText>
			<reportElement x="455" y="25" width="555" height="15" style="eMaku-Font6" positionType="FixRelativeToTop" stretchType="NoStretch" isPrintRepeatedValues="true" isRemoveLineWhenBlank="false" isPrintInFirstWholeBand="false" isPrintWhenDetailOverflows="false" />
			<textElement>
				<font />
			</textElement>
			<text><![CDATA[Iva]]></text>
		</staticText>
		<staticText>
			<reportElement x="515" y="25" width="555" height="15" style="eMaku-Font6" positionType="FixRelativeToTop" stretchType="NoStretch" isPrintRepeatedValues="true" isRemoveLineWhenBlank="false" isPrintInFirstWholeBand="false" isPrintWhenDetailOverflows="false" />
			<textElement>
				<font />
			</textElement>
			<text><![CDATA[Total]]></text>
		</staticText>
			<textField isStretchWithOverflow="false" evaluationTime="Now" hyperlinkType="None" hyperlinkTarget="Self" bookmarkLevel="0">
					<reportElement x="30" y="0" width="180" height="20" style="eMaku-Font6" positionType="FixRelativeToTop" stretchType="NoStretch" isPrintRepeatedValues="true" isRemoveLineWhenBlank="false" isPrintInFirstWholeBand="false" isPrintWhenDetailOverflows="false" />
			<textElement />
				<textFieldExpression class="java.lang.String">
					<![CDATA[$F{descr_grupo}]]>
				</textFieldExpression>
			</textField>
			</band>
		</groupHeader>
		<groupFooter>
			<band height="0" isSplitAllowed="true" />
		</groupFooter>
	</group>
	<title>
		<band height="0" isSplitAllowed="true" />
	</title>
	<pageHeader>
		<band height="80" isSplitAllowed="true">
			<textField isStretchWithOverflow="false" evaluationTime="Now" hyperlinkType="None" hyperlinkTarget="Self" bookmarkLevel="0">
				<reportElement x="50" y="0" width="555" height="25" style="eMaku-Font4" positionType="FixRelativeToTop" stretchType="NoStretch" isPrintRepeatedValues="true" isRemoveLineWhenBlank="false" isPrintInFirstWholeBand="false" isPrintWhenDetailOverflows="false" />
				<textElement />
				<textFieldExpression class="java.lang.String">
					<![CDATA[$P{Empresa}]]>
				</textFieldExpression>
			</textField>
			<textField isStretchWithOverflow="false" evaluationTime="Now" hyperlinkType="None" hyperlinkTarget="Self" bookmarkLevel="0">
				<reportElement x="50" y="18" width="555" height="25" style="eMaku-Font4" positionType="FixRelativeToTop" stretchType="NoStretch" isPrintRepeatedValues="true" isRemoveLineWhenBlank="false" isPrintInFirstWholeBand="false" isPrintWhenDetailOverflows="false" />
				<textElement />
				<textFieldExpression class="java.lang.String">
					<![CDATA["Nit: " + $P{Nit}]]>
				</textFieldExpression>
			</textField>
			<textField isStretchWithOverflow="false" evaluationTime="Now" hyperlinkType="None" hyperlinkTarget="Self" bookmarkLevel="0">
				<reportElement x="50" y="36" width="555" height="25" style="eMaku-Font4" positionType="FixRelativeToTop" stretchType="NoStretch" isPrintRepeatedValues="true" isRemoveLineWhenBlank="false" isPrintInFirstWholeBand="false" isPrintWhenDetailOverflows="false" />
				<textElement />
				<textFieldExpression class="java.lang.String">
					<![CDATA["Fecha: " + $P{Fecha}]]>
				</textFieldExpression>
			</textField>
			<textField isStretchWithOverflow="false" evaluationTime="Now" hyperlinkType="None" hyperlinkTarget="Self" bookmarkLevel="0">
				<reportElement x="0" y="0" width="520" height="15" style="eMaku-Font2" positionType="FixRelativeToTop" stretchType="NoStretch" isPrintRepeatedValues="true" isRemoveLineWhenBlank="false" isPrintInFirstWholeBand="false" isPrintWhenDetailOverflows="false" />
				<textElement textAlignment="Right" />
				<textFieldExpression class="java.lang.String">
					<![CDATA["P치gina " + String.valueOf($V{PAGE_NUMBER})]]>
				</textFieldExpression>
			</textField>
			<textField isStretchWithOverflow="false" evaluationTime="Now" hyperlinkType="None" hyperlinkTarget="Self" bookmarkLevel="0">
				<reportElement x="0" y="65" width="555" height="15" style="eMaku-Font5" positionType="FixRelativeToTop" stretchType="NoStretch" isPrintRepeatedValues="true" isRemoveLineWhenBlank="false" isPrintInFirstWholeBand="false" isPrintWhenDetailOverflows="false">
					<printWhenExpression>
						<![CDATA[new Boolean($V{PAGE_NUMBER}.intValue() == 1)]]>
					</printWhenExpression>
				</reportElement>
				<textElement textAlignment="Center">
					<font size="12" />
				</textElement>
				<textFieldExpression class="java.lang.String">
					<![CDATA[String.valueOf("LISTA DE PRECIOS")]]>
				</textFieldExpression>
			</textField>
		</band>
	</pageHeader>
	<columnHeader>
		<band height="10" isSplitAllowed="true">
                        </band>
	</columnHeader>
	<detail>
		<band height="15" isSplitAllowed="true">
<rectangle>
<reportElement x="0" y="0" width="555" height="10" forecolor="#000000" backcolor="#efefef" positionType="FixRelativeToTop" stretchType="NoStretch" isPrintRepeatedValues="true" isRemoveLineWhenBlank="false" isPrintInFirstWholeBand="false" isPrintWhenDetailOverflows="false" />
<graphicElement />
</rectangle>
			<textField isStretchWithOverflow="false" evaluationTime="Now" hyperlinkType="None" hyperlinkTarget="Self" bookmarkLevel="0">
				<reportElement x="30" y="0" width="100" height="15" style="eMaku-Font2" positionType="FixRelativeToTop" stretchType="NoStretch" isPrintRepeatedValues="true" isRemoveLineWhenBlank="false" isPrintInFirstWholeBand="false" isPrintWhenDetailOverflows="false" />
				<textElement />
				<textFieldExpression class="java.lang.String">
					<![CDATA[$F{codigo}]]>
				</textFieldExpression>
			</textField>
			<textField isStretchWithOverflow="false" evaluationTime="Now" hyperlinkType="None" hyperlinkTarget="Self" bookmarkLevel="0">
				<reportElement x="110" y="0" width="250" height="15" style="eMaku-Font2" positionType="FixRelativeToTop" stretchType="NoStretch" isPrintRepeatedValues="true" isRemoveLineWhenBlank="false" isPrintInFirstWholeBand="false" isPrintWhenDetailOverflows="false" />
				<textElement />
				<textFieldExpression class="java.lang.String">
					<![CDATA[$F{descr_producto}]]>
				</textFieldExpression>
			</textField>
			<textField isStretchWithOverflow="false" evaluationTime="Now" hyperlinkType="None" hyperlinkTarget="Self" bookmarkLevel="0">
				<reportElement x="270" y="0" width="100" height="15" style="eMaku-Font2" positionType="FixRelativeToTop" stretchType="NoStretch" isPrintRepeatedValues="true" isRemoveLineWhenBlank="false" isPrintInFirstWholeBand="false" isPrintWhenDetailOverflows="false" />
				<textElement textAlignment="Right" />
				<textFieldExpression class="java.lang.String">
					<![CDATA[new java.text.DecimalFormat("#,###,##0.00").format($F{pcompra})]]>
				</textFieldExpression>
			</textField>
			<textField isStretchWithOverflow="false" evaluationTime="Now" hyperlinkType="None" hyperlinkTarget="Self" bookmarkLevel="0">
				<reportElement x="255" y="0" width="180" height="15" style="eMaku-Font2" positionType="FixRelativeToTop" stretchType="NoStretch" isPrintRepeatedValues="true" isRemoveLineWhenBlank="false" isPrintInFirstWholeBand="false" isPrintWhenDetailOverflows="false" />
				<textElement textAlignment="Right" />
				<textFieldExpression class="java.lang.String">
                                                            <![CDATA[new java.text.DecimalFormat("#,###,##0.00").format($F{pventa})]]>
				</textFieldExpression>
			</textField>
			<textField isStretchWithOverflow="false" evaluationTime="Now" hyperlinkType="None" hyperlinkTarget="Self" bookmarkLevel="0">
				<reportElement x="365" y="0" width="100" height="15" style="eMaku-Font2" positionType="FixRelativeToTop" stretchType="NoStretch" isPrintRepeatedValues="true" isRemoveLineWhenBlank="false" isPrintInFirstWholeBand="false" isPrintWhenDetailOverflows="false" />
				<textElement textAlignment="Right" />
				<textFieldExpression class="java.lang.String">
					<![CDATA[$F{iva}]]>
				</textFieldExpression>
			</textField>
			<textField isStretchWithOverflow="false" evaluationTime="Now" hyperlinkType="None" hyperlinkTarget="Self" bookmarkLevel="0">
				<reportElement x="450" y="0" width="100" height="15" style="eMaku-Font2" positionType="FixRelativeToTop" stretchType="NoStretch" isPrintRepeatedValues="true" isRemoveLineWhenBlank="false" isPrintInFirstWholeBand="false" isPrintWhenDetailOverflows="false" />
				<textElement textAlignment="Right" />
				<textFieldExpression class="java.lang.String">
					<![CDATA[new java.text.DecimalFormat("#,###,##0.00").format($F{neto})]]>
				</textFieldExpression>
			</textField>
		</band>
	</detail>
	<columnFooter>
		<band height="10" isSplitAllowed="true" />
	</columnFooter>
	<pageFooter>
		<band height="15" isSplitAllowed="true">
			<textField hyperlinkType="Reference" hyperlinkTarget="Blank" isStretchWithOverflow="false" evaluationTime="Now" bookmarkLevel="0">
				<reportElement x="20" y="0" width="520" height="15" style="eMaku-Font2" positionType="FixRelativeToTop" stretchType="NoStretch" isPrintRepeatedValues="true" isRemoveLineWhenBlank="false" isPrintInFirstWholeBand="false" isPrintWhenDetailOverflows="false" forecolor="blue" />
			<textElement />
			<textFieldExpression class="java.lang.String"><![CDATA[$P{Qhatu}]]></textFieldExpression>
				<hyperlinkReferenceExpression><![CDATA[$P{Url}]]></hyperlinkReferenceExpression>
			</textField>
			<textField isStretchWithOverflow="false" evaluationTime="Now" hyperlinkType="None" hyperlinkTarget="Self" bookmarkLevel="0">
				<reportElement x="0" y="0" width="520" height="15" style="eMaku-Font2" positionType="FixRelativeToTop" stretchType="NoStretch" isPrintRepeatedValues="true" isRemoveLineWhenBlank="false" isPrintInFirstWholeBand="false" isPrintWhenDetailOverflows="false" />
				<textElement textAlignment="Right" />
				<textFieldExpression class="java.lang.String">
					<![CDATA["P치gina " + String.valueOf($V{PAGE_NUMBER}) + " de "]]>
				</textFieldExpression>
			</textField>
			<textField evaluationTime="Report" isStretchWithOverflow="false" hyperlinkType="None" hyperlinkTarget="Self" bookmarkLevel="0">
				<reportElement x="518" y="0" width="520" height="15" style="eMaku-Font2" positionType="FixRelativeToTop" stretchType="NoStretch" isPrintRepeatedValues="true" isRemoveLineWhenBlank="false" isPrintInFirstWholeBand="false" isPrintWhenDetailOverflows="false" />
				<textElement textAlignment="Left" />
				<textFieldExpression class="java.lang.String">
					<![CDATA[" " + String.valueOf($V{PAGE_NUMBER})]]>
				</textFieldExpression>
			</textField>
		</band>
	</pageFooter>
</jasperReport>
